autologic/__init__.py
autologic/cli.py
autologic/config.py
autologic/gemini.py
autologic/localLLM.py
autologic/openai.py
autologic/reasoningEngine.py
autologic/utils.py
autologic-0.0.3.dist-info/LICENSE
autologic-0.0.3.dist-info/METADATA
autologic-0.0.3.dist-info/WHEEL
autologic-0.0.3.dist-info/entry_points.txt
autologic-0.0.3.dist-info/top_level.txt
autologic-0.0.3.dist-info/RECORD
