Metadata-Version: 2.1
Name: autologic
Version: 0.0.3
Summary: A framework for LLMs to self-compose reasoning structures
Author-email: Konstantin Kerekovski <kerekovskik@gmail.com>
License: Apache-2.0
Project-URL: Repository, https://github.com/waszumteufel/autologic
Keywords: LLMs,framework,reasoning structures
Classifier: Programming Language :: Python :: 3
Classifier: License :: OSI Approved :: Apache Software License
Classifier: Operating System :: OS Independent
Classifier: Programming Language :: Python :: 3.8
Classifier: Programming Language :: Python :: 3.9
Classifier: Programming Language :: Python :: 3.10
Classifier: Programming Language :: Python :: 3.11
Requires-Python: >=3.8
License-File: LICENSE
Requires-Dist: python-dotenv
Requires-Dist: google-generativeai
Requires-Dist: llama-cpp-python
Requires-Dist: openai
